bsdiffhs/cli.py
bsdiffhs/core.cpython-310-powerpc64le-linux-gnu.so
bsdiffhs/format.py
bsdiffhs/__init__.py
bsdiffhs/test_all.py
bsdiffhs-0.3.0.dist-info/METADATA
bsdiffhs-0.3.0.dist-info/LICENSE
bsdiffhs-0.3.0.dist-info/entry_points.txt
bsdiffhs-0.3.0.dist-info/WHEEL
bsdiffhs-0.3.0.dist-info/RECORD
bsdiffhs-0.3.0.dist-info/top_level.txt
