Metadata-Version: 2.1
Name: bsdiffhs
Version: 0.3.0
Summary: binary diff and patch using the BSDIFFHS-format
Home-page: https://github.com/RomainPelletant/bsdiffhs
Author: Kickmaker
Author-email: romainp@kickmaker.net
License: BSD
Classifier: Development Status :: 5 - Production/Stable
Classifier: Intended Audience :: Developers
Classifier: Operating System :: OS Independent
Classifier: Programming Language :: C
Classifier: Programming Language :: Python :: 3.7
Classifier: Programming Language :: Python :: 3.8
Classifier: Programming Language :: Python :: 3.9
Classifier: Programming Language :: Python :: 3.10
Classifier: Programming Language :: Python :: 3.11
Classifier: Programming Language :: Python :: 3.12
Classifier: Topic :: Utilities
License-File: LICENSE
Requires-Dist: heatshrink2
